pii_optimized_logger/__init__.py
pii_optimized_logger/log_handler.py
pii_optimized_logger-0.0.8.dist-info/METADATA
pii_optimized_logger-0.0.8.dist-info/WHEEL
pii_optimized_logger-0.0.8.dist-info/licenses/LICENSE
pii_optimized_logger-0.0.8.dist-info/RECORD
