Metadata-Version: 2.1
Name: pii_optimized_logger
Version: 0.0.8
Summary: Handler to mask data and optimized the log volume
Project-URL: Homepage, https://github.com/
Project-URL: Bug Tracker, https://github.com/
Author-email: "NewStore Inc." <dev@newstore.com>
Maintainer-email: Fabien Thetis <fthetis@newstore.com>
License-File: LICENSE
Classifier: License :: OSI Approved :: MIT License
Classifier: Operating System :: OS Independent
Classifier: Programming Language :: Python :: 3
Requires-Python: >=3.7
